setup.py
udacity_test_project_jk8/Binomialdistribution.py
udacity_test_project_jk8/Gaussiandistribution.py
udacity_test_project_jk8/Generaldistribution.py
udacity_test_project_jk8/__init__.py
udacity_test_project_jk8.egg-info/PKG-INFO
udacity_test_project_jk8.egg-info/SOURCES.txt
udacity_test_project_jk8.egg-info/dependency_links.txt
udacity_test_project_jk8.egg-info/not-zip-safe
udacity_test_project_jk8.egg-info/top_level.txt