Metadata-Version: 1.0
Name: udacity-test-project-jk8
Version: 0.1
Summary: Gaussian distributions
Home-page: UNKNOWN
Author: Jonas Kircher
Author-email: UNKNOWN
License: UNKNOWN
Platform: UNKNOWN
